{
  "users": [
    {
      "id": "492e42f1-bf5c-4ee6-b74c-b5bbf9585d94",
      "updated_date": "17-02-2019 09:34:23:367+00:00",
      "firstName": "Madden",
      "lastName": "Long",
      "email": "madden.long@kidgrease.name",
      "age": 35,
      "phone": [
        {
          "id": "22017e4c-a872-4364-8faf-08a2d2cf91ea",
          "number": "(963) 511-2731",
          "type": "home",
          "primary": false
        }
      ],
      "address": {
        "line1": "988 Everit Street",
        "line2": "Kings Hwy",
        "line3": "Stuart Street",
        "line4": "",
        "city": "Cassel",
        "state": "South Dakota",
        "zipcode": 3235,
        "country": "Ukraine"
      }
    },
    {
      "id": "025b3430-cef1-46bf-a4f2-71603809bb6e",
      "updated_date": "17-02-2019 09:34:23:372+00:00",
      "firstName": "Crosby",
      "lastName": "Buckner",
      "email": "crosby.buckner@parcoe.biz",
      "age": 32,
      "phone": [
        {
          "id": "dffe1a9b-0a1a-4f41-91e1-103b4cf7e748",
          "number": "(980) 514-2665",
          "type": "home",
          "primary": true
        },
        {
          "id": "c61cac80-b468-4e33-9c78-0769cce170b6",
          "number": "(826) 550-2735",
          "type": "home",
          "primary": true
        }
      ],
      "address": {
        "line1": "804 Arkansas Drive",
        "line2": "Hendrix Street",
        "line3": "Buffalo Avenue",
        "line4": "",
        "city": "Stockwell",
        "state": "Wyoming",
        "zipcode": 806,
        "country": "Namibia"
      }
    },
    {
      "id": "4f5d9e23-19b6-4ceb-9201-78fbe5b4c1d3",
      "updated_date": "17-02-2019 09:34:23:373+00:00",
      "firstName": "Ashley",
      "lastName": "Solomon",
      "email": "ashley.solomon@yogasm.org",
      "age": 45,
      "phone": [
        {
          "id": "de9ba032-80bb-4a5d-9109-efaf0e83ffcc",
          "number": "(928) 482-2427",
          "type": "mobile",
          "primary": true
        },
        {
          "id": "54e6144a-733f-4c38-8950-bc5134c19224",
          "number": "(848) 436-2448",
          "type": "mobile",
          "primary": true
        }
      ],
      "address": {
        "line1": "122 Grant Avenue",
        "line2": "Gatling Place",
        "line3": "Polar Street",
        "line4": "",
        "city": "Ferney",
        "state": "Vermont",
        "zipcode": 5187,
        "country": "Brazil"
      }
    },
    {
      "id": "853df8f5-2c6a-48e6-b363-8842f80754b7",
      "updated_date": "17-02-2019 09:34:23:373+00:00",
      "firstName": "Casey",
      "lastName": "Newton",
      "email": "casey.newton@cyclonica.me",
      "age": 30,
      "phone": [
        {
          "id": "67dbdf78-49ec-4592-bc5e-9f817baac805",
          "number": "(986) 589-3801",
          "type": "mobile",
          "primary": false
        }
      ],
      "address": {
        "line1": "983 Rodney Street",
        "line2": "Ashford Street",
        "line3": "Greene Avenue",
        "line4": "",
        "city": "Smock",
        "state": "Indiana",
        "zipcode": 1356,
        "country": "Kenya"
      }
    },
    {
      "id": "e05e1e0a-de89-454c-8741-7ec55184bcb3",
      "updated_date": "17-02-2019 09:34:23:373+00:00",
      "firstName": "Helen",
      "lastName": "Nicholson",
      "email": "helen.nicholson@nixelt.io",
      "age": 72,
      "phone": [
        {
          "id": "94bc7768-e24a-4cc2-9cba-f9d1f2be96fa",
          "number": "(829) 586-3102",
          "type": "others",
          "primary": false
        }
      ],
      "address": {
        "line1": "259 Dearborn Court",
        "line2": "Malbone Street",
        "line3": "Billings Place",
        "line4": "",
        "city": "Hall",
        "state": "Virgin Islands",
        "zipcode": 6662,
        "country": "US Minor Outlying Islands"
      }
    },
    {
      "id": "a35d7833-88b9-4ef9-a8d8-0db07d4ffb78",
      "updated_date": "17-02-2019 09:34:23:374+00:00",
      "firstName": "Alisa",
      "lastName": "Vasquez",
      "email": "alisa.vasquez@buzzopia.tv",
      "age": 72,
      "phone": [
        {
          "id": "bd9b3548-3b77-4207-8f4e-da5d8703f0b3",
          "number": "(812) 480-2955",
          "type": "others",
          "primary": true
        }
      ],
      "address": {
        "line1": "544 Calder Place",
        "line2": "Halsey Street",
        "line3": "Independence Avenue",
        "line4": "",
        "city": "Derwood",
        "state": "Wisconsin",
        "zipcode": 6265,
        "country": "Russian Federation"
      }
    },
    {
      "id": "99fc6603-bc15-4900-aff7-f9fd62cea797",
      "updated_date": "17-02-2019 09:34:23:374+00:00",
      "firstName": "Nola",
      "lastName": "Richmond",
      "email": "nola.richmond@entroflex.co.uk",
      "age": 73,
      "phone": [
        {
          "id": "0028a7a6-a9fd-4fc8-a4dc-3cba43d9603d",
          "number": "(894) 561-2571",
          "type": "home",
          "primary": true
        }
      ],
      "address": {
        "line1": "638 Drew Street",
        "line2": "Boerum Street",
        "line3": "Roosevelt Court",
        "line4": "",
        "city": "Spelter",
        "state": "Nevada",
        "zipcode": 7994,
        "country": "Western Sahara"
      }
    },
    {
      "id": "2a7ee398-426a-41c6-bfa8-8ad20dd6b336",
      "updated_date": "17-02-2019 09:34:23:374+00:00",
      "firstName": "Hampton",
      "lastName": "Cortez",
      "email": "hampton.cortez@darwinium.net",
      "age": 38,
      "phone": [
        {
          "id": "f75ee6e2-95c7-402e-9fe7-2676d132123f",
          "number": "(802) 559-2195",
          "type": "mobile",
          "primary": false
        }
      ],
      "address": {
        "line1": "137 Girard Street",
        "line2": "Concord Street",
        "line3": "Church Lane",
        "line4": "",
        "city": "Abiquiu",
        "state": "Marshall Islands",
        "zipcode": 8134,
        "country": "Botswana"
      }
    },
    {
      "id": "60469c0a-b496-4ce7-a84e-d86515b89ef1",
      "updated_date": "17-02-2019 09:34:23:374+00:00",
      "firstName": "Shelia",
      "lastName": "Marquez",
      "email": "shelia.marquez@zillactic.info",
      "age": 41,
      "phone": [
        {
          "id": "50b8a434-5520-4be1-908f-11d0bc5cb87a",
          "number": "(902) 513-2606",
          "type": "home",
          "primary": true
        }
      ],
      "address": {
        "line1": "927 Dinsmore Place",
        "line2": "Cyrus Avenue",
        "line3": "Sullivan Place",
        "line4": "",
        "city": "Chemung",
        "state": "North Dakota",
        "zipcode": 6511,
        "country": "Saudi Arabia"
      }
    },
    {
      "id": "45f7b8ae-ef5a-4f39-85ca-19ca8e0b8ba7",
      "updated_date": "17-02-2019 09:34:23:375+00:00",
      "firstName": "Prince",
      "lastName": "Walton",
      "email": "prince.walton@twiggery.ca",
      "age": 40,
      "phone": [
        {
          "id": "72692125-b30f-45e0-8fb2-02cad3dc786a",
          "number": "(966) 509-3763",
          "type": "home",
          "primary": true
        },
        {
          "id": "8f7e172a-9e42-42e5-9a39-82f5fadf5113",
          "number": "(874) 411-3523",
          "type": "home",
          "primary": true
        }
      ],
      "address": {
        "line1": "425 Royce Place",
        "line2": "Oceanview Avenue",
        "line3": "Albemarle Road",
        "line4": "",
        "city": "Bath",
        "state": "Tennessee",
        "zipcode": 9435,
        "country": "Algeria"
      }
    },
    {
      "id": "b1a53fee-1941-47ee-afd5-bcf129a6164e",
      "updated_date": "17-02-2019 09:34:23:375+00:00",
      "firstName": "Vanessa",
      "lastName": "Mcmillan",
      "email": "vanessa.mcmillan@comveyor.com",
      "age": 68,
      "phone": [
        {
          "id": "12e73881-6e64-4d3a-9d91-41e75fd8dda5",
          "number": "(958) 437-2389",
          "type": "others",
          "primary": false
        }
      ],
      "address": {
        "line1": "854 Waldane Court",
        "line2": "Howard Place",
        "line3": "Thomas Street",
        "line4": "",
        "city": "Jackpot",
        "state": "Kentucky",
        "zipcode": 9083,
        "country": "Cayman Islands"
      }
    },
    {
      "id": "2b9d625f-6e3b-417c-8cc7-b371feddf775",
      "updated_date": "17-02-2019 09:34:23:375+00:00",
      "firstName": "Cynthia",
      "lastName": "Galloway",
      "email": "cynthia.galloway@plexia.us",
      "age": 60,
      "phone": [
        {
          "id": "44d8fdfe-4b98-42c8-92f5-1c93724b1533",
          "number": "(890) 475-2368",
          "type": "others",
          "primary": true
        },
        {
          "id": "9fbbcb32-9c65-447d-8282-eabf2b2866ca",
          "number": "(906) 416-2232",
          "type": "home",
          "primary": false
        }
      ],
      "address": {
        "line1": "321 Navy Walk",
        "line2": "Durland Place",
        "line3": "Grimes Road",
        "line4": "",
        "city": "Manitou",
        "state": "Palau",
        "zipcode": 9989,
        "country": "Malta"
      }
    }
  ],
  "profile": {
    "name": "typicode"
  }
}
